CONTRIBUTORS
LICENSE
README.md
research_kit/VERSION
research_kit/__init__.py
research_kit/__main__.py
research_kit/__version__.py
research_kit/artists.py
research_kit/data_import.py
research_kit/fit.py
research_kit/format_conversions.py
research_kit/quick.py
research_kit-0.1.1.dist-info/LICENSE
research_kit-0.1.1.dist-info/METADATA
research_kit-0.1.1.dist-info/WHEEL
research_kit-0.1.1.dist-info/entry_points.txt
research_kit-0.1.1.dist-info/top_level.txt
research_kit-0.1.1.dist-info/RECORD
